modern_di/__init__.py
modern_di/container.py
modern_di/group.py
modern_di/py.typed
modern_di/scope.py
modern_di/types.py
modern_di/types_parser.py
modern_di/providers/__init__.py
modern_di/providers/abstract.py
modern_di/providers/context_provider.py
modern_di/providers/factory.py
modern_di/providers/object.py
modern_di/registries/__init__.py
modern_di/registries/cache_registry.py
modern_di/registries/context_registry.py
modern_di/registries/providers_registry.py
modern_di-2.2.0.dist-info/METADATA
modern_di-2.2.0.dist-info/WHEEL
modern_di-2.2.0.dist-info/RECORD
